{
  "projects": "projects",
  "achievements": "achievements",
  "Athar_CHarity": "Athar CHarity",
  "serach": "Search for a project...",
  "Volunteer": "Volunteer campaigns",
  "emergeny" : "Emergency campaigns",
  "cart": "Donation Basket",
  "setting": "Setting",
  "language": "language",
  "profile": "profile",
  "Notifications": "Notifications",
  "Themes": "Themes",
  "Log out": "Log out",
  "Request for help": "Request help",
  "sorry dont project":  "☹️ Sorry, there are no projects. ",
  " sorrrr dont achievements":  "☹️ Sorry, there are no achievements so far. ",
  "emergency1": "There is little left until the end of the campaign.",
  "fiald campaign": "Failed to load the campaigns",
"Description of the case": "Description of the case:",
  "the Description": "This patient is in an emergency situation, so if you're thinking of donating, don't hesitate; every good deed you plant will be multiplied after a while; save a soul.",
  ":الوقت المتبقي": "Remaining time:",
  ": المبلغ الكلي": "The Total amount:",
  ": المبلغ المحصل": "Amount collected:",
  ": المبلغ المتبقي":"Remaining amount:",
  "تبرع الآن": "Donate now",
  "اختر اللغة": "Select language",
  "الرجاء اختيار لغة التطبيق" :"Please select the application language.",
  "تعديل الملف الشخصي":"Edit Profile",
  "تغيير اللغة": "Change language",
  "تغيير السمة": "Change the theme",
  "تسجيل دخول كمحتاج": "Login as a needy person",
  "استلام إِشعارات التطبيق": "Receiving application notifications",
  "الخروج من التطبيق": "Log out of the application",
  "الرجاء تسجيل الدخول اولا": "Please log in first.",
  "تأكيد تسجيل الخروج": "Confirm Logout",
  "أدخل مبلغ التبرع": "Enter the donation amount",
  "المبلغ": "the amount",
  "إلغاء": "Cancellation",
"الرجاء إدخال مبلغ صحيح": "Please enter a valid amount.",
  "موافق": "confirm",
  "عذراً، هذا المشروع اكتمل": "Sorry, this project is completed.",
  "تبرعك يتجاوز حد المبلغ المتبقي للمشروع": "Your donation exceeds the remaining amount for the project.",
  "تم التبرع بمبلغ": "An amount has been donated",
  "للمشروع": "For the project",
  "السلة فارغة": "The basket is empty",
  "تأكيد الحذف": "Confirm deletion",
  "عذراً، لا يوجد رصيد كافي. يرجى شحن المحفظة": "Sorry, there is not enough balance. Please recharge the wallet.",
  "حذف": "Are you sure you want to delete?",
  "لا": "No",
  "نعم": "yes",
  "مبلغ": "Amount",
  "تأكيد التبرع": "Donation Confirmation",
  ":الإجمالي": "Total:",
  "فشل تحميل السلة": "Failed to load the cart",
  "أدخل مبلغ التبرع الجديد": "Enter the new donation amount",
  "الرجاء إدخال رقم صحيح": "Please enter a valid number.",
  "تم التسجيل بنجاح": "Registration successful!",
  "العمر": "Age:",
  "المبلغ": "The Amount",
  "الجنس": "Gender ",
  "الاحتياجات": "The needs",
  "التبرعات": "Donations",
  "المبالغ": "The Amounts",
  "النسبة": "The percentage of donations collected",
  ": ادخل المبلغ المراد التبرع به": "Enter the amount you wish to donate:",
  "تبرع": "Donation",
  "تبرعك يتجاوز حد المبلغ المتبقي للمشروع": "Your donation exceeds the remaining amount for the project.",
  "عذراً، هذا المشروع اكتمل": "Sorry, this project is completed.",
  "لا توجد احتياجات محددة لهذا التبرع": "There are no specific needs for this donation.",
  "أضف للسلة": "Add to cart",
  "إنشاء حساب": "Create an account",
  "سجل دخول كمتبرع": "Register as a donor",
  "الاسم الأول": "First name",
  "الاسم الأخير": "Last name",
  "البريد الإلكتروني": "Email",
  "كلمة المرور": "Password",
  "تأكيد كلمة المرور": "Confirm Password",
  "سجل دخول": "Login",
  "هل لديك حساب؟": "Do you have an account?",
  "معلوماتك الشخصية": "Your personal information",
  "يرجى إدخال الاسم الكامل": "Please enter the full name",
  "الاسم الثلاثي": "Full name",
  "رقم الهاتف": "Phone number",
  "العنوان": "Location",
  "التالي": "Next",
  "تطوع الآن": "Volunteer now",
  "الخبرات": "The experiences",
  "المهارات": "The skills",
  "مهاراتك وخبراتك التطوعية": "Your skills and volunteer experiences",
  "هل أنت متأكد من تسجيل الخروج من التطبيق؟": "Are you sure you want to log out of the app?",
  "مرحباً": "Hello",
  "سجل دخول كمستفيد": "Log in as a beneficiary",
  "يرجى إدخال  الاسم والكنية": "Please enter the first name and surname.",
  "الاسم والكنية": "Name and the nickname",
  "يرجى إدخال اسم الأب": "Please enter the father's name.",
  "اسم الأب": "Father's name",
  "يرجى إدخال اسم الأم": "Please enter the mother's name.",
  "اسم الأم": "Mother's name",
  "يرجى إدخال العنوان": "Please enter the address.",
  "يرجى إدخال البريد الالكتروني": "Please enter the email.",
  "يرجى إدخال رقم الهاتف": "Please enter the phone number.",
  "يرجى إدخال  كلمة المرور": "Please enter the password.",
  "يرجى إدخال تأكيد كلمة المرور":"Please enter the password confirmation.",
  "كلمة المرور غير متطابقة ": "The password does not match.",
  "يرجى ملء جميع الحقول بشكل صحيح": "Please fill in all fields correctly.",
  "هل تحتاج إلى مساعدة؟": "Do you need help?",
  "يمكنك طلب مساعدة الآن أو لاحقًا من خلال القائمة": "You can request help now or later through the menu.",
  "طلب مساعدة": "Request for help",
  "لاحقاً": "Later",
  "الدخل المادي": "The financial income",
  "العمل": "Work",
  "الحالة الاجتماعية": "The marital status",
  "الحالة الصحية": "The health condition",
  "عدد أفراد العائلة": "Number of family members",
  "تسجيل الطلب": "Order Registration",
  "تعديل مبلغ التبرع لـ": "Adjust the donation amount to:",
  " حذف": "Remove ",
  "المحفظة": "Wallet",
  "رصيد المحفظة": "Wallet balance",
  "شحن المحفظة بمبلغ: ": "Charge the wallet with the amount of:",
  "الرجاء إدخال رقم صحيح": "Please enter a valid number",
  "أدخل مبلغ الشحن": "Enter the shipping amount",
  "شحن المحفظة": "Wallet top-up",
  "سجل معلوماتك لطلب المساعدة": "Register you information",
  "ذكر": "Male",
  "أنثى": "Female",
  "هل الحالة طارئة": "Is the situation urgent?",
  "يرجى اختيار الجنس أولاً": "Please select the gender first.",
  "متزوج": "Married",
  "أعزب": "Single",
  "هل لديك عائلة": "Do you have a family?",
  "هل أنت معيل عائلة": "Are you the breadwinner of the family?",
  "هل أنت شاب بدون عائلة": "Are you a young person without a family?",
  "هل أنت يتيم ؟": "Are you an orphan?",
  "هل أنت مصاب ؟": "Are you injured?",
  "متزوجة": "Married",
  "عزباء": "Single",
  "هل أنتِ معيلة عائلة ": "Are you the breadwinner of the family?",
  "هل أنتِ فتاة بدون عائلة": "Are you a girl without a family?",
  "هل أنتِ يتيمة ؟": "Are you an orphan?",
  "هل أنتِ مصابة ؟": "Are you injured?",
  "الاحتياجات الخاصة": "Are you a person with disabilities?",
  "يرجى إدخال الحالة الصحية": "Please enter the health status",
  "يرجى إدخال العمل الحالي": "Please enter the current work.",
  "يرجى إدخال المدخول الشهري": "Please enter the monthly income.",
  "يرجى إدخال نوع الدعم المراد": "Please enter the type of support you need.",
  "نوع الدعم المراد": "Type of support required",
  "يرجى إدخال عدد الأطفال": "Please enter the number of children.",
  "يرجى إدخال عدد الأطفال ذوي الاحتياجات الخاصة": "Please enter the number of children with special needs.",
  "يرجى إدخال الاحتياجات": "Please enter the requirements.",
  "تسجيل الطلب": "Order Registration",
  "تم تسجيل طلبك يرجى مراجعة الاشعارات لتفقده": "Your request has been recorded, please check the notifications to review it.",
  "عدد الأطفال ذوي الاحتياجات ": "Number of children with disabilities",
  "عدد الأطفال": "Number of children",
  "المدخول الشهري": "Monthly income",
  "العمل الحالي ": "The current work",
  "الحالة الصحية": "The health condition",
  "جمعية أثر": "ATHAR",
  "تعديل الملف الشخصي": "Edit Profile",
  "تأكيد التعديل": "Confirmation of the amendment",
  "يرجى تسجيل الدخول كمتطوع اولاً": "Please log in as a volunteer first.",
  "يمكنك الانضمام للحملة الان او لاحقاً.": "You can join the campaign now or later.",
  "هل أنت متأكد من الانضمام للحملة؟": "Are you sure about joining the campaign?",
  "أنت مسجل مسبقًا": "You are already registered.",
  "تم انضمامك بنجاح": "You have successfully joined.",
  "يرجى تسجيل الدخول كمتطوع أولاً": "Please log in as a volunteer first.",
  "انضمام للحملة": "Join the campaign"
}
